codesys_bridge/__init__.py
codesys_bridge/codesys_script_install.py
codesys_bridge/cs_export.py
codesys_bridge/export.py
codesys_bridge/export_sync.py
codesys_bridge/load.py
codesys_bridge/test_tree_parser.py
codesys_bridge/assets/export_icon.ico
codesys_bridge/assets/git.ico
codesys_bridge-0.1.5.dist-info/METADATA
codesys_bridge-0.1.5.dist-info/WHEEL
codesys_bridge-0.1.5.dist-info/entry_points.txt
codesys_bridge-0.1.5.dist-info/top_level.txt
codesys_bridge-0.1.5.dist-info/RECORD
